git_lock_sign_jlx/__init__.py
git_lock_sign_jlx/_version.py
git_lock_sign_jlx/backend_logger_util.py
git_lock_sign_jlx/extension.py
git_lock_sign_jlx/handlers.py
git_lock_sign_jlx/services/__init__.py
git_lock_sign_jlx/services/sidecar_client.py
git_lock_sign_jlx-0.1.1.data/data/share/jupyter/labextensions/git_lock_sign_jlx/package.json
git_lock_sign_jlx-0.1.1.data/data/share/jupyter/labextensions/git_lock_sign_jlx/schemas/git_lock_sign_jlx/package.json.orig
git_lock_sign_jlx-0.1.1.data/data/share/jupyter/labextensions/git_lock_sign_jlx/schemas/git_lock_sign_jlx/plugin.json
git_lock_sign_jlx-0.1.1.data/data/share/jupyter/labextensions/git_lock_sign_jlx/static/151.286fb65cda5f7c06107a.js
git_lock_sign_jlx-0.1.1.data/data/share/jupyter/labextensions/git_lock_sign_jlx/static/654.13f3aa2c4d2191111e84.js
git_lock_sign_jlx-0.1.1.data/data/share/jupyter/labextensions/git_lock_sign_jlx/static/728.02bdaddf557722cdd316.js
git_lock_sign_jlx-0.1.1.data/data/share/jupyter/labextensions/git_lock_sign_jlx/static/remoteEntry.649e0022f4714f66ad2e.js
git_lock_sign_jlx-0.1.1.data/data/share/jupyter/labextensions/git_lock_sign_jlx/static/style.js
git_lock_sign_jlx-0.1.1.data/data/share/jupyter/labextensions/git_lock_sign_jlx/static/third-party-licenses.json
git_lock_sign_jlx-0.1.1.data/data/share/jupyter/labextensions/git_lock_sign_jlx/install.json
git_lock_sign_jlx-0.1.1.dist-info/METADATA
git_lock_sign_jlx-0.1.1.dist-info/WHEEL
git_lock_sign_jlx-0.1.1.dist-info/entry_points.txt
git_lock_sign_jlx-0.1.1.dist-info/licenses/LICENSE
git_lock_sign_jlx-0.1.1.dist-info/RECORD
