Metadata-Version: 2.4
Name: git_lock_sign_jlx
Version: 0.1.1
Summary: A JupyterLab extension.
Project-URL: Homepage, https://github.com/liuji1031/git_lock_sign_jlx
Project-URL: Bug Tracker, https://github.com/liuji1031/git_lock_sign_jlx/issues
Project-URL: Repository, https://github.com/liuji1031/git_lock_sign_jlx.git
Author-email: Ji Liu <ji.liu@axleinfo.com>
License: BSD 3-Clause License
License-File: LICENSE
Keywords: jupyter,jupyterlab,jupyterlab-extension
Classifier: Framework :: Jupyter
Classifier: Framework :: Jupyter :: JupyterLab
Classifier: Framework :: Jupyter :: JupyterLab :: 4
Classifier: Framework :: Jupyter :: JupyterLab :: Extensions
Classifier: Framework :: Jupyter :: JupyterLab :: Extensions :: Prebuilt
Classifier: License :: OSI Approved :: BSD License
Classifier: Programming Language :: Python
Classifier: Programming Language :: Python :: 3
Classifier: Programming Language :: Python :: 3.9
Classifier: Programming Language :: Python :: 3.10
Classifier: Programming Language :: Python :: 3.11
Classifier: Programming Language :: Python :: 3.12
Classifier: Programming Language :: Python :: 3.13
Requires-Python: >=3.9
Requires-Dist: aiohttp>=3.9.0
Requires-Dist: jupyter-server>=2.0.0
Requires-Dist: python-dotenv>=1.0.0
Requires-Dist: requests>=2.25.0
Requires-Dist: tornado>=6.0.0
